forcetable/__init__.py
forcetable/_field.py
forcetable/_record.py
forcetable/_table.py
forcetable/exceptions.py
forcetable-0.0.5.dist-info/LICENSE
forcetable-0.0.5.dist-info/METADATA
forcetable-0.0.5.dist-info/WHEEL
forcetable-0.0.5.dist-info/top_level.txt
forcetable-0.0.5.dist-info/RECORD
